{
    "alpha2_code": "DJ",
    "short_name": "DJIBOUTI",
    "short_name_lower_case": "Djibouti",
    "full_name": "the Republic of Djibouti",
    "alpha3_code": "DJI",
    "numeric_code": 262,
    "remarks": null,
    "independent": "Yes",
    "territory_name": null,
    "status": "Officially assigned",
    "subdivisions": [
        {
            "category": "region",
            "3166-2_code": "DJ-AS",
            "name": "Ali Sabieh",
            "local_variant": null,
            "language_code": "fr",
            "romanization_system": null,
            "parent_subdivision": null
        },
        {
            "category": "region",
            "3166-2_code": "DJ-AR",
            "name": "Arta",
            "local_variant": null,
            "language_code": "fr",
            "romanization_system": null,
            "parent_subdivision": null
        },
        {
            "category": "region",
            "3166-2_code": "DJ-OB",
            "name": "Awbūk",
            "local_variant": null,
            "language_code": "ar",
            "romanization_system": "BGN/PCGN 1956",
            "parent_subdivision": null
        },
        {
            "category": "region",
            "3166-2_code": "DJ-DI",
            "name": "Dikhil",
            "local_variant": null,
            "language_code": "fr",
            "romanization_system": null,
            "parent_subdivision": null
        },
        {
            "category": "region",
            "3166-2_code": "DJ-DI",
            "name": "Dikhīl",
            "local_variant": null,
            "language_code": "ar",
            "romanization_system": "BGN/PCGN 1956",
            "parent_subdivision": null
        },
        {
            "category": "city",
            "3166-2_code": "DJ-DJ",
            "name": "Djibouti",
            "local_variant": null,
            "language_code": "fr",
            "romanization_system": null,
            "parent_subdivision": null
        },
        {
            "category": "city",
            "3166-2_code": "DJ-DJ",
            "name": "Jībūtī",
            "local_variant": null,
            "language_code": "ar",
            "romanization_system": "BGN/PCGN 1956",
            "parent_subdivision": null
        },
        {
            "category": "region",
            "3166-2_code": "DJ-OB",
            "name": "Obock",
            "local_variant": null,
            "language_code": "fr",
            "romanization_system": null,
            "parent_subdivision": null
        },
        {
            "category": "region",
            "3166-2_code": "DJ-TA",
            "name": "Tadjourah",
            "local_variant": null,
            "language_code": "fr",
            "romanization_system": null,
            "parent_subdivision": null
        },
        {
            "category": "region",
            "3166-2_code": "DJ-TA",
            "name": "Tājūrah",
            "local_variant": null,
            "language_code": "ar",
            "romanization_system": "BGN/PCGN 1956",
            "parent_subdivision": null
        },
        {
            "category": "region",
            "3166-2_code": "DJ-AS",
            "name": "‘Alī Şabīḩ",
            "local_variant": null,
            "language_code": "ar",
            "romanization_system": "BGN/PCGN 1956",
            "parent_subdivision": null
        },
        {
            "category": "region",
            "3166-2_code": "DJ-AR",
            "name": "‘Artā",
            "local_variant": null,
            "language_code": "ar",
            "romanization_system": "BGN/PCGN 1956",
            "parent_subdivision": null
        }
    ],
    "additional_information": [
        {
            "administrative_language_alpha2": "ar",
            "administrative_language_alpha3": "ara",
            "local_short_name": "Jībūtī"
        },
        {
            "administrative_language_alpha2": "fr",
            "administrative_language_alpha3": "fra",
            "local_short_name": "Djibouti"
        }
    ]
}