{
    "alpha2_code": "PW",
    "short_name": "PALAU",
    "short_name_lower_case": "Palau",
    "full_name": "the Republic of Palau",
    "alpha3_code": "PLW",
    "numeric_code": 585,
    "remarks": null,
    "independent": "Yes",
    "territory_name": "Babelthuap (principal island), the west part of the Caroline Islands",
    "status": "Officially assigned",
    "subdivision_categories": [
        {
            "category_count": 16,
            "category_locales": [
                "state (en)",
                "État (fr)"
            ]
        }
    ],
    "subdivisions": [
        {
            "category": "state",
            "3166-2_code": "PW-002",
            "name": "Aimeliik",
            "local_variant": null,
            "language_code": "en",
            "romanization_system": null,
            "parent_subdivision": null
        },
        {
            "category": "state",
            "3166-2_code": "PW-002",
            "name": "Aimeliik",
            "local_variant": null,
            "language_code": "-",
            "romanization_system": null,
            "parent_subdivision": null
        },
        {
            "category": "state",
            "3166-2_code": "PW-004",
            "name": "Airai",
            "local_variant": null,
            "language_code": "en",
            "romanization_system": null,
            "parent_subdivision": null
        },
        {
            "category": "state",
            "3166-2_code": "PW-004",
            "name": "Airai",
            "local_variant": null,
            "language_code": "-",
            "romanization_system": null,
            "parent_subdivision": null
        },
        {
            "category": "state",
            "3166-2_code": "PW-010",
            "name": "Angaur",
            "local_variant": null,
            "language_code": "en",
            "romanization_system": null,
            "parent_subdivision": null
        },
        {
            "category": "state",
            "3166-2_code": "PW-010",
            "name": "Angaur",
            "local_variant": null,
            "language_code": "-",
            "romanization_system": null,
            "parent_subdivision": null
        },
        {
            "category": "state",
            "3166-2_code": "PW-050",
            "name": "Hatohobei",
            "local_variant": null,
            "language_code": "en",
            "romanization_system": null,
            "parent_subdivision": null
        },
        {
            "category": "state",
            "3166-2_code": "PW-050",
            "name": "Hatohobei",
            "local_variant": null,
            "language_code": "-",
            "romanization_system": null,
            "parent_subdivision": null
        },
        {
            "category": "state",
            "3166-2_code": "PW-100",
            "name": "Kayangel",
            "local_variant": null,
            "language_code": "en",
            "romanization_system": null,
            "parent_subdivision": null
        },
        {
            "category": "state",
            "3166-2_code": "PW-100",
            "name": "Kayangel",
            "local_variant": null,
            "language_code": "-",
            "romanization_system": null,
            "parent_subdivision": null
        },
        {
            "category": "state",
            "3166-2_code": "PW-150",
            "name": "Koror",
            "local_variant": null,
            "language_code": "en",
            "romanization_system": null,
            "parent_subdivision": null
        },
        {
            "category": "state",
            "3166-2_code": "PW-150",
            "name": "Koror",
            "local_variant": null,
            "language_code": "-",
            "romanization_system": null,
            "parent_subdivision": null
        },
        {
            "category": "state",
            "3166-2_code": "PW-212",
            "name": "Melekeok",
            "local_variant": null,
            "language_code": "en",
            "romanization_system": null,
            "parent_subdivision": null
        },
        {
            "category": "state",
            "3166-2_code": "PW-212",
            "name": "Melekeok",
            "local_variant": null,
            "language_code": "-",
            "romanization_system": null,
            "parent_subdivision": null
        },
        {
            "category": "state",
            "3166-2_code": "PW-214",
            "name": "Ngaraard",
            "local_variant": null,
            "language_code": "en",
            "romanization_system": null,
            "parent_subdivision": null
        },
        {
            "category": "state",
            "3166-2_code": "PW-214",
            "name": "Ngaraard",
            "local_variant": null,
            "language_code": "-",
            "romanization_system": null,
            "parent_subdivision": null
        },
        {
            "category": "state",
            "3166-2_code": "PW-218",
            "name": "Ngarchelong",
            "local_variant": null,
            "language_code": "en",
            "romanization_system": null,
            "parent_subdivision": null
        },
        {
            "category": "state",
            "3166-2_code": "PW-218",
            "name": "Ngarchelong",
            "local_variant": null,
            "language_code": "-",
            "romanization_system": null,
            "parent_subdivision": null
        },
        {
            "category": "state",
            "3166-2_code": "PW-222",
            "name": "Ngardmau",
            "local_variant": null,
            "language_code": "en",
            "romanization_system": null,
            "parent_subdivision": null
        },
        {
            "category": "state",
            "3166-2_code": "PW-222",
            "name": "Ngardmau",
            "local_variant": null,
            "language_code": "-",
            "romanization_system": null,
            "parent_subdivision": null
        },
        {
            "category": "state",
            "3166-2_code": "PW-224",
            "name": "Ngatpang",
            "local_variant": null,
            "language_code": "en",
            "romanization_system": null,
            "parent_subdivision": null
        },
        {
            "category": "state",
            "3166-2_code": "PW-224",
            "name": "Ngatpang",
            "local_variant": null,
            "language_code": "-",
            "romanization_system": null,
            "parent_subdivision": null
        },
        {
            "category": "state",
            "3166-2_code": "PW-226",
            "name": "Ngchesar",
            "local_variant": null,
            "language_code": "en",
            "romanization_system": null,
            "parent_subdivision": null
        },
        {
            "category": "state",
            "3166-2_code": "PW-226",
            "name": "Ngchesar",
            "local_variant": null,
            "language_code": "-",
            "romanization_system": null,
            "parent_subdivision": null
        },
        {
            "category": "state",
            "3166-2_code": "PW-227",
            "name": "Ngeremlengui",
            "local_variant": null,
            "language_code": "en",
            "romanization_system": null,
            "parent_subdivision": null
        },
        {
            "category": "state",
            "3166-2_code": "PW-227",
            "name": "Ngeremlengui",
            "local_variant": null,
            "language_code": "-",
            "romanization_system": null,
            "parent_subdivision": null
        },
        {
            "category": "state",
            "3166-2_code": "PW-228",
            "name": "Ngiwal",
            "local_variant": null,
            "language_code": "en",
            "romanization_system": null,
            "parent_subdivision": null
        },
        {
            "category": "state",
            "3166-2_code": "PW-228",
            "name": "Ngiwal",
            "local_variant": null,
            "language_code": "-",
            "romanization_system": null,
            "parent_subdivision": null
        },
        {
            "category": "state",
            "3166-2_code": "PW-350",
            "name": "Peleliu",
            "local_variant": null,
            "language_code": "en",
            "romanization_system": null,
            "parent_subdivision": null
        },
        {
            "category": "state",
            "3166-2_code": "PW-350",
            "name": "Peleliu",
            "local_variant": null,
            "language_code": "-",
            "romanization_system": null,
            "parent_subdivision": null
        },
        {
            "category": "state",
            "3166-2_code": "PW-370",
            "name": "Sonsorol",
            "local_variant": null,
            "language_code": "en",
            "romanization_system": null,
            "parent_subdivision": null
        },
        {
            "category": "state",
            "3166-2_code": "PW-370",
            "name": "Sonsorol",
            "local_variant": null,
            "language_code": "-",
            "romanization_system": null,
            "parent_subdivision": null
        }
    ],
    "additional_information": [
        {
            "administrative_language_alpha2": "en",
            "administrative_language_alpha3": "eng",
            "local_short_name": "Palau"
        },
        {
            "administrative_language_alpha2": "-",
            "administrative_language_alpha3": "pau",
            "local_short_name": "Belau"
        }
    ],
    "change_history": [
        {
            "date": "2016-11-15",
            "short_description_en": "Change of spelling of PW-050 in eng, pau; update list source",
            "short_description_fr": "Modification de l'orthographe de PW-050 en eng, pau; mise à jour de la Liste Source"
        }
    ]
}